{
  "sections": {
    "hero": {
      "type": "section-hero",
      "settings": {
        "bg_position": "center-center",
        "height": "use_screen_one_fifth",
        "overlay_opacity": 50,
        "overlay_color": "#000000",
        "kicker": "",
        "title": "Our story",
        "richtext": "",
        "text_align": "align--middle-center",
        "text_color": "text--white",
        "link_text": "",
        "link": "",
        "button_color": "btn--white",
        "button_style": "btn"
      }
    },
    "main": {
      "type": "page",
      "settings": {
        "kicker": "",
        "show_title": false,
        "show_content": true,
        "text_size": 2,
        "align_text": "text-left",
        "height": "margin--large",
        "width": "wrapper",
        "text_color": "text--neutral",
        "bg": "palette--light bg--neutral"
      }
    },
    "custom-content-2": {
      "type": "section-custom-content",
      "blocks": {
        "custom-content-2-0": {
          "type": "text",
          "settings": {
            "kicker": "Humble beginnings",
            "title": "",
            "text": "<p>Our story begins in a small shop with a small team. With nothing but passion and a dream our brand was born. <\/p>",
            "text_size": 2,
            "text_columns": 1,
            "align_text": "text-left",
            "button_text": "",
            "button_url": "",
            "button_color": "btn--neutral",
            "button_style": "caps--link",
            "text_color": "text--neutral",
            "bg_color": "#f7f7f7"
          }
        },
        "custom-content-2-1": {
          "type": "video",
          "settings": {
            "video_link_bg": "",
            "object_position": "center-center",
            "bg_position": "center-center",
            "video_link": "",
            "popup_text": "",
            "kicker": "",
            "title": "",
            "richtext": "",
            "text_align": "align--middle-center",
            "text_color": "text--white",
            "overlay_opacity": 50,
            "overlay_color": "#000000",
            "link_text": "Our Pledge",
            "link": "shopify:\/\/pages\/faq",
            "button_color": "btn--white",
            "button_style": "btn--soft"
          }
        }
      },
      "block_order": [
        "custom-content-2-0",
        "custom-content-2-1"
      ],
      "settings": {
        "height": "use_screen_one_half",
        "padding": true,
        "borders": false,
        "wrapper": true
      }
    },
    "custom-content-1": {
      "type": "section-custom-content",
      "blocks": {
        "custom-content-1-0": {
          "type": "video",
          "settings": {
            "video_link_bg": "",
            "object_position": "center-center",
            "bg_position": "center-center",
            "video_link": "https:\/\/www.youtube.com\/watch?v=_9VUPq3SxOc",
            "popup_text": "Learn our story",
            "kicker": "",
            "title": "",
            "richtext": "",
            "text_align": "align--middle-center",
            "text_color": "text--white",
            "overlay_opacity": 55,
            "overlay_color": "#000000",
            "link_text": "",
            "link": "",
            "button_color": "btn--white",
            "button_style": "btn"
          }
        },
        "custom-content-1-1": {
          "type": "text",
          "settings": {
            "kicker": "Quality first",
            "title": "",
            "text": "<p>We started making the products we wanted to see in the world and we did this with an uncompromising approach to sustainability.<\/p>",
            "text_size": 2,
            "text_columns": 1,
            "align_text": "text-left",
            "button_text": "",
            "button_url": "",
            "button_color": "btn--neutral",
            "button_style": "caps--link",
            "text_color": "text--neutral",
            "bg_color": "#f7f7f7"
          }
        }
      },
      "block_order": [
        "custom-content-1-0",
        "custom-content-1-1"
      ],
      "settings": {
        "height": "use_screen_one_half",
        "padding": true,
        "borders": false,
        "wrapper": true
      }
    },
    "icons": {
      "type": "section-icons",
      "blocks": {
        "icons-0": {
          "type": "icon_block",
          "settings": {
            "icon_name": "icon-basket-return",
            "icon_color": "#aaaaaa",
            "title": "Free returns",
            "text": "<p>Returns within 30 days receive a full refund.<\/p>"
          }
        },
        "icons-1": {
          "type": "icon_block",
          "settings": {
            "icon_name": "icon-shipment-world",
            "icon_color": "#aaaaaa",
            "title": "Worldwide shipping",
            "text": "<p>Ship anywhere, rates available at checkout.<\/p>"
          }
        },
        "icons-2": {
          "type": "icon_block",
          "settings": {
            "icon_name": "icon-phone",
            "icon_color": "#aaaaaa",
            "title": "24\/7 support",
            "text": "<p>Call us anytime at 1(800) 555-1234.<\/p>"
          }
        }
      },
      "block_order": [
        "icons-0",
        "icons-1",
        "icons-2"
      ],
      "settings": {
        "title": "",
        "bg": "palette--light bg--accent",
        "icon_size": "icon--medium",
        "icon_alignment": "icon--top",
        "align_text": "text-left"
      }
    }
  },
  "order": [
    "hero",
    "main",
    "custom-content-2",
    "custom-content-1",
    "icons"
  ]
}