{
  "sections": {
    "main": {
      "type": "page",
      "disabled": true,
      "settings": {
        "kicker": "",
        "show_title": true,
        "show_content": true,
        "text_size": 1,
        "align_text": "text-left",
        "height": "margin--small",
        "width": "wrapper",
        "text_color": "text--neutral",
        "bg": "palette--light bg--neutral"
      }
    },
    "16529718191567e479": {
      "type": "section-hero",
      "settings": {
        "image": "shopify:\/\/shop_images\/pexels-cottonbro-4909808.jpg",
        "bg_position": "center-center",
        "height": "use_screen_one_half",
        "overlay_opacity": 25,
        "overlay_color": "#000000",
        "kicker": "",
        "title": "Let Us Help Plan Your Project",
        "richtext": "",
        "text_align": "align--middle-center",
        "text_color": "text--white",
        "enable_search": false,
        "link_text": "",
        "link": "",
        "button_color": "btn--white",
        "button_style": "btn"
      }
    },
    "1652971871795fc3c4": {
      "type": "section-richtext",
      "blocks": {
        "1652971871a9685616-1": {
          "type": "heading",
          "settings": {
            "heading": "<p>Don't Know Where To Start?<\/p>",
            "text_size": 8
          }
        },
        "1652971871a9685616-2": {
          "type": "text",
          "settings": {
            "text": "<p>At FenceFast we have over a decade of highly specialized experience setting up fencing and animal management systems. <\/p><p>Fill out the form below and let us help you plan yours!<\/p>",
            "text_size": 5,
            "text_columns": 1
          }
        }
      },
      "block_order": [
        "1652971871a9685616-1",
        "1652971871a9685616-2"
      ],
      "settings": {
        "align_text": "text-center",
        "height": "margin--medium",
        "width": "wrapper",
        "bg": "palette--light bg--neutral"
      }
    },
    "16529719377fe63b43": {
      "type": "section-contact",
      "blocks": {
        "f3031328-81d8-4258-8ea7-492b7f79db99": {
          "type": "form_heading",
          "settings": {
            "title": "Contact Information"
          }
        },
        "16529719365296cd45-0": {
          "type": "text",
          "settings": {
            "title": "Full Name"
          }
        },
        "16529719365296cd45-1": {
          "type": "email",
          "settings": {
            "title": "Email"
          }
        },
        "ca7821a3-5014-4e61-bd8a-58fccab354a9": {
          "type": "telephone",
          "settings": {
            "title": "Phone Number (optional)"
          }
        },
        "31706fe6-380f-48be-96a4-a9a8cf612fe9": {
          "type": "form_heading",
          "settings": {
            "title": "Project Details"
          }
        },
        "486992b8-4f4f-43f8-857e-e9b0ce11af39": {
          "type": "text",
          "settings": {
            "title": "Size of project\/dimensions"
          }
        },
        "2ddb8435-fa5a-45f0-9715-0612d8da02d5": {
          "type": "text",
          "settings": {
            "title": "What are you trying to keep in?"
          }
        },
        "73988554-e437-4215-9968-28e58dcf1607": {
          "type": "text",
          "settings": {
            "title": "What are you trying to keep out?"
          }
        },
        "3721f3bf-f62a-4616-bc46-fa9224a64705": {
          "type": "text",
          "settings": {
            "title": "Where are you located?"
          }
        },
        "2de8dc3f-6e49-423e-9cb5-94db20899290": {
          "type": "text",
          "settings": {
            "title": "Do you have existing fencing?"
          }
        },
        "0f3610e4-c53f-4e86-b5e0-1661b9018206": {
          "type": "form_heading",
          "settings": {
            "title": "Tell us a little more about your project"
          }
        },
        "16529719365296cd45-2": {
          "type": "body",
          "settings": {
            "title": "Project Details"
          }
        }
      },
      "block_order": [
        "f3031328-81d8-4258-8ea7-492b7f79db99",
        "16529719365296cd45-0",
        "16529719365296cd45-1",
        "ca7821a3-5014-4e61-bd8a-58fccab354a9",
        "31706fe6-380f-48be-96a4-a9a8cf612fe9",
        "486992b8-4f4f-43f8-857e-e9b0ce11af39",
        "2ddb8435-fa5a-45f0-9715-0612d8da02d5",
        "73988554-e437-4215-9968-28e58dcf1607",
        "3721f3bf-f62a-4616-bc46-fa9224a64705",
        "2de8dc3f-6e49-423e-9cb5-94db20899290",
        "0f3610e4-c53f-4e86-b5e0-1661b9018206",
        "16529719365296cd45-2"
      ],
      "settings": {
        "title": "",
        "align_text": "text-left",
        "height": "margin--small",
        "width": "wrapper--narrow",
        "text_color": "text--neutral",
        "bg": "palette--light bg--accent"
      }
    },
    "1652972753e5879bd5": {
      "type": "section-custom-content",
      "blocks": {
        "9ba4632d-7db1-4adc-b866-fda91a8ab954": {
          "type": "image",
          "settings": {
            "image": "shopify:\/\/shop_images\/pexels-spencer-selover-775418.jpg",
            "bg_position": "center-top",
            "overlay_opacity": 35,
            "overlay_color": "#000",
            "kicker": "",
            "title": "Browse out our guides and advice",
            "richtext": "We've compiled a repository of guides and advice to common fencing and animal solutions.",
            "text_align": "align--middle-center",
            "text_color": "text--white",
            "link_text": "Explore Guides & Advice",
            "link": "shopify:\/\/blogs\/guides-advice",
            "button_color": "btn--primary",
            "button_style": "btn uppercase"
          }
        }
      },
      "block_order": [
        "9ba4632d-7db1-4adc-b866-fda91a8ab954"
      ],
      "settings": {
        "height": "use_screen_one_half",
        "padding": false,
        "borders": false,
        "wrapper": true
      }
    }
  },
  "order": [
    "main",
    "16529718191567e479",
    "1652971871795fc3c4",
    "16529719377fe63b43",
    "1652972753e5879bd5"
  ]
}